ezshare/__main__.py
ezshare-0.0.11.dist-info/LICENSE.TXT
ezshare-0.0.11.dist-info/METADATA
ezshare-0.0.11.dist-info/WHEEL
ezshare-0.0.11.dist-info/entry_points.txt
ezshare-0.0.11.dist-info/top_level.txt
ezshare-0.0.11.dist-info/RECORD
