Metadata-Version: 2.1
Name: ezshare
Version: 0.0.11
Summary: A simple library and commandline tool to access EzShare WiFi SD Cards
Author-email: Andrew 'Necromant' Andrianov <andrew@ncrmnt.org>
License: DO WHAT THE FUCK YOU WANT TO PUBLIC LICENSE
Project-URL: Homepage, https://github.com/nekromant/python-ezshare
Project-URL: Bug Tracker, https://github.com/nekromant/python-ezshare/issues
Classifier: Programming Language :: Python :: 3
Classifier: License :: Public Domain
Classifier: Operating System :: OS Independent
Requires-Python: >=3.7
License-File: LICENSE.TXT
Requires-Dist: requests (>=2)
Requires-Dist: lxml (>=4.6)
Requires-Dist: tqdm (>=4.6)
Requires-Dist: parse (>=1.18)
